LICENSE
MANIFEST.in
README
README.md
setup.py
opencl4py.egg-info/PKG-INFO
opencl4py.egg-info/SOURCES.txt
opencl4py.egg-info/dependency_links.txt
opencl4py.egg-info/requires.txt
opencl4py.egg-info/top_level.txt
src/opencl4py/__init__.py
src/opencl4py/_cffi.py
src/opencl4py/_py.py
src/opencl4py/blas/__init__.py
src/opencl4py/blas/_clblas.py
tests/test.cl
tests/test_api.py
tests/test_clblas.py