Metadata-Version: 1.1
Name: opencl4py
Version: 1.3.7
Summary: OpenCL cffi bindings and helper classes
Home-page: https://github.com/Samsung/opencl4py
Author: Samsung Electronics Co.,Ltd.
Author-email: a.kazantsev@samsung.com
License: Simplified BSD
Download-URL: https://github.com/Samsung/opencl4py
Keywords: OpenCL,clBLAS,opencl4py
Platform: UNKNOWN
Classifier: Development Status :: 4 - Beta
Classifier: Environment :: Console
Classifier: Intended Audience :: Developers
Classifier: License :: OSI Approved :: BSD License
Classifier: Operating System :: POSIX
Classifier: Programming Language :: Python :: 2.7
Classifier: Programming Language :: Python :: 3.2
Classifier: Programming Language :: Python :: 3.3
Classifier: Programming Language :: Python :: 3.4
Classifier: Topic :: Software Development :: Libraries
